Workbook

Sheet Menu Principal
A1: AGREGADOR E ORGANIZADOR DE IMPOSTO DE RENDA (IRPF)
A3: Painel Central de Navegação e Links Úteis da Receita Federal
A5: NAVEGAÇÃO RÁPIDA (MÓDULOS DA PLANILHA)
B6: 1. RENDIMENTOS | E6: Informe salários, pro-labore, aluguéis, dividendos e rendimentos isentos.
B9: 2. BENS E DIREITOS | E9: Controle de imóveis, veículos, contas bancárias, ações e FIIs.
B12: 3. DESPESAS DEDUTÍVEIS | E12: Cadastro de gastos com saúde, educação, previdência e dependentes.
B15: 4. RESUMO DA DECLARAÇÃO | E15: Visão consolidada do imposto, totais por categoria e pendências.
A18: LINKS RÁPIDOS & RECURSOS OFICIAIS (RECEITA FEDERAL)
A19: Recurso / Ferramenta | B19: Link Oficial | C19: Descrição / Utilidade
A20: Portal Meu Imposto de Renda (e-CAC) | B20: Acessar Portal | C20: Acesse sua declaração pré-preenchida e verifique pendências na malha fina.
A21: Download do Programas do IRPF | B21: Acessar Portal | C21: Baixe o programa oficial para Windows, Mac ou Linux.
A22: Consulta Restituição do IRPF | B22: Acessar Portal | C22: Consulte o status e lote de pagamento da sua restituição.
A23: Perguntão IRPF (Guia Oficial de Dúvidas) | B23: Acessar Portal | C23: Manual tira-dúvidas oficial com todas as regras atualizadas.

Sheet Rendimentos
A1: MÓDULO 1: RENDIMENTOS RECEBIDOS NO ANO
A3: ◄ Voltar ao Menu Principal
A5: Tipo de Rendimento | B5: Fonte Pagadora / Empresa | C5: CNPJ / CPF da Fonte | D5: Rendimento Bruto (R$) | E5: Imposto Retido na Fonte (R$) | F5: INSS / Previdência (R$) | G5: 13º Salário (R$) | H5: Observações / Comprovante
A6: Tributável (Salário/Pro-Labore) | B6: Empresa Exemplo S.A. | C6: 00.000.000/0001-00 | D6: 85000 | E6: 12500 | F6: 7500 | G6: 7000 | H6: Informe de Rendimentos RH
A26: TOTAL CONSOLIDADO | D26: =SUM(D6:D25) | E26: =SUM(E6:E25) | F26: =SUM(F6:F25) | G26: =SUM(G6:G25)

Sheet Bens e Direitos
A1: MÓDULO 2: BENS E DIREITOS (PATRIMÔNIO)
A3: ◄ Voltar ao Menu Principal
A5: Grupo / Código IRPF | B5: Discriminação / Descrição do Bem | C5: Instituição / Localização | D5: Situação em 31/12/Ano Ant. (R$) | E5: Situação em 31/12/Ano Atual (R$) | F5: Variação Patrimonial (R$) | G5: Documento / Matrícula / Renavam
A6: 01 - Bens Imóveis | B6: Apartamento Residencial 75m² - SP | C6: Cartório de Imóveis SP | D6: 350000 | E6: 350000 | F6: =E6-D6 | G6: Matrícula 123.456
F7: =E7-D7
F8: =E8-D8
F9: =E9-D9
F10: =E10-D10
F11: =E11-D11
F12: =E12-D12
F13: =E13-D13
F14: =E14-D14
F15: =E15-D15
F16: =E16-D16
F17: =E17-D17
F18: =E18-D18
... F25: =E25-D25
A26: PATRIMÔNIO TOTAL | D26: =SUM(D6:D25) | E26: =SUM(E6:E25) | F26: =SUM(F6:F25)

Sheet Despesas Dedutíveis
A1: MÓDULO 3: DESPESAS DEDUTÍVEIS E PAGAMENTOS EFETUADOS
A3: ◄ Voltar ao Menu Principal
A5: Categoria da Despesa | B5: Nome do Beneficiário / Prestador | C5: CPF / CNPJ do Prestador | D5: Valor Pago (R$) | E5: Valor Dedutível Estimado (R$) | F5: Comprovante / Recibo Anexado?
A6: Saúde (Médicos/Planos) | B6: Plano de Saúde Bradesco | C6: 00.123.456/0001-99 | D6: 6400 | E6: =IF(A6="Instrução/Educação", MIN(D6, 3561.5), IF(A6="Saúde (Médicos/Planos)", D6, D6)) | F6: SIM
E7: =IF(A7="Instrução/Educação", MIN(D7, 3561.5), IF(A7="Saúde (Médicos/Planos)", D7, D7))
E8: =IF(A8="Instrução/Educação", MIN(D8, 3561.5), IF(A8="Saúde (Médicos/Planos)", D8, D8))
E9: =IF(A9="Instrução/Educação", MIN(D9, 3561.5), IF(A9="Saúde (Médicos/Planos)", D9, D9))
E10: =IF(A10="Instrução/Educação", MIN(D10, 3561.5), IF(A10="Saúde (Médicos/Planos)", D10, D10))
E11: =IF(A11="Instrução/Educação", MIN(D11, 3561.5), IF(A11="Saúde (Médicos/Planos)", D11, D11))
E12: =IF(A12="Instrução/Educação", MIN(D12, 3561.5), IF(A12="Saúde (Médicos/Planos)", D12, D12))
E13: =IF(A13="Instrução/Educação", MIN(D13, 3561.5), IF(A13="Saúde (Médicos/Planos)", D13, D13))
E14: =IF(A14="Instrução/Educação", MIN(D14, 3561.5), IF(A14="Saúde (Médicos/Planos)", D14, D14))
E15: =IF(A15="Instrução/Educação", MIN(D15, 3561.5), IF(A15="Saúde (Médicos/Planos)", D15, D15))
E16: =IF(A16="Instrução/Educação", MIN(D16, 3561.5), IF(A16="Saúde (Médicos/Planos)", D16, D16))
E17: =IF(A17="Instrução/Educação", MIN(D17, 3561.5), IF(A17="Saúde (Médicos/Planos)", D17, D17))
E18: =IF(A18="Instrução/Educação", MIN(D18, 3561.5), IF(A18="Saúde (Médicos/Planos)", D18, D18))
... E25: =IF(A25="Instrução/Educação", MIN(D25, 3561.5), IF(A25="Saúde (Médicos/Planos)", D25, D25))
A26: TOTAL DEDUÇÕES | D26: =SUM(D6:D25) | E26: =SUM(E6:E25)

Sheet Resumo IR
A1: MÓDULO 4: RESUMO CONSOLIDADO DA DECLARAÇÃO
A3: ◄ Voltar ao Menu Principal
A5: DASHBOARD PATRIMONIAL E TRIBUTÁRIO
A6: TOTAL RENDIMENTOS | C6: IMPOSTO RETIDO (IRRF) | E6: TOTAL DESPESAS DEDUTÍVEIS | G6: PATRIMÔNIO ATUAL TOTAL
A7: =Rendimentos!D26 | C7: =Rendimentos!E26 | E7: ='Despesas Dedutíveis'!E26 | G7: ='Bens e Direitos'!E26
A10: DISCRIMINAÇÃO CONSOLIDADA PARA O PROGRAMA DA RECEITA
A11: Categoria IRPF | D11: Valor Apurado (R$) | E11: Origem dos Dados
A12: Total de Rendimentos Tributáveis | D12: =Rendimentos!D26 | E12: Aba Rendimentos (Soma Coluna D)
A13: Total de Imposto de Renda Retido na Fonte | D13: =Rendimentos!E26 | E13: Aba Rendimentos (Soma Coluna E)
A14: Total de Contribuição Previdenciária (INSS) | D14: =Rendimentos!F26 | E14: Aba Rendimentos (Soma Coluna F)
A15: Total de Despesas Dedutíveis Estimadas | D15: ='Despesas Dedutíveis'!E26 | E15: Aba Despesas (Soma Coluna E)
A16: Patrimônio Total Declarado (31/12) | D16: ='Bens e Direitos'!E26 | E16: Aba Bens e Direitos (Soma Coluna E)
A17: Variação Patrimonial no Ano | D17: ='Bens e Direitos'!F26 | E17: Aba Bens e Direitos (Soma Coluna F)
A20: CHECKLIST DE PENDÊNCIAS E COMPROVANTES
A21: Documento / Comprovante Necessário | E21: Status de Coleta
A22: Informe de Rendimentos do Trabalho (Empresas/RH) | E22: OK
A23: Informes de Rendimentos de Bancos e Corretoras | E23: OK
A24: Comprovantes de Despesas Médicas e Planos de Saúde | E24: OK
A25: Comprovantes de Cursos / Mensalidades Escolares | E25: OK
A26: Extrato de Quitação de Financiamento Imobiliário/Veículos | E26: OK
